<?xml version="1.0" encoding="UTF-8"?>
<!-- ***************************************************************** -->
<!--                                                                   -->
<!-- IBM Confidential                                                  -->
<!--                                                                   -->
<!-- OCO Source Materials                                              -->
<!--                                                                   -->
<!-- Copyright IBM Corp. 2011, 2016                                    -->
<!--                                                                   -->
<!-- The source code for this program is not published or otherwise    -->
<!-- divested of its trade secrets, irrespective of what has been      -->
<!-- deposited with the U.S. Copyright Office.                         -->
<!--                                                                   -->
<!-- ***************************************************************** -->

<messagebundle>  
  <msg name="title">Datoteke</msg>
  <msg name="description">Pripomoček Datoteke, ki omogoča nalaganje in souporabljanje datotek</msg>
  <msg name="action_uploadFile_label">Datoteke</msg>
  <msg name="action_uploadFile_tooltip">Naložite in souporabljajte datoteke</msg>
  <msg name="loading">Nalaganje ...</msg>
  <msg name="error_msg">Vsebine ni mogoče naložiti. Poskusite znova pozneje ali se obrnite na skrbnika.</msg>
  <msg name="error_alt">Napaka</msg>
</messagebundle>
